[
    {
        "policy_hash": "0f1f33e6b2f4313c5ec42ddbd85923f5",
        "starts_on": 319,
        "ends_on": 334,
        "selection_class": "ThirdParty",
        "selection_content": "третьим лицам"
    },
    {
        "policy_hash": "0f1f33e6b2f4313c5ec42ddbd85923f5",
        "starts_on": 1717,
        "ends_on": 1733,
        "selection_class": "ThirdParty",
        "selection_content": "третьим лицам."
    },
    {
        "policy_hash": "40c0d54264cfcec50f09354959ec1ae4",
        "starts_on": 3392,
        "ends_on": 3512,
        "selection_class": "ThirdParty",
        "selection_content": ". 2. сайт использует службы google analytics, яндекс. метрика и других третьих сторон, которые собирают статистику для"
    },
    {
        "policy_hash": "40c0d54264cfcec50f09354959ec1ae4",
        "starts_on": 5022,
        "ends_on": 5145,
        "selection_class": "ThirdParty",
        "selection_content": ", может быть использована для отправки владельцам ссылающихся интернет сайтов актуальной информации, касающейся изменений"
    },
    {
        "policy_hash": "40c0d54264cfcec50f09354959ec1ae4",
        "starts_on": 5689,
        "ends_on": 5736,
        "selection_class": "ThirdParty",
        "selection_content": "уполномоченным органам государственной власти"
    },
    {
        "policy_hash": "40c0d54264cfcec50f09354959ec1ae4",
        "starts_on": 6796,
        "ends_on": 6809,
        "selection_class": "ThirdParty",
        "selection_content": "третьих лиц"
    },
    {
        "policy_hash": "5b72951d5972661758b139950195af9f",
        "starts_on": 3191,
        "ends_on": 3249,
        "selection_class": "ThirdParty",
        "selection_content": "на сайте счетчики компании yandex/rambler/google и т. п."
    },
    {
        "policy_hash": "5b72951d5972661758b139950195af9f",
        "starts_on": 5953,
        "ends_on": 5970,
        "selection_class": "ThirdParty",
        "selection_content": "третьими лицами"
    },
    {
        "policy_hash": "5b72951d5972661758b139950195af9f",
        "starts_on": 7667,
        "ends_on": 7682,
        "selection_class": "ThirdParty",
        "selection_content": "третьим лицам"
    },
    {
        "policy_hash": "5b72951d5972661758b139950195af9f",
        "starts_on": 10639,
        "ends_on": 10659,
        "selection_class": "ThirdParty",
        "selection_content": "поставщиков услуг,"
    },
    {
        "policy_hash": "5b72951d5972661758b139950195af9f",
        "starts_on": 10867,
        "ends_on": 10884,
        "selection_class": "ThirdParty",
        "selection_content": "третьими лицами"
    },
    {
        "policy_hash": "6a056e2b58f4d2e3b0cd119184fb815c",
        "starts_on": 7317,
        "ends_on": 7335,
        "selection_class": "ThirdParty",
        "selection_content": "поставщики услуг"
    },
    {
        "policy_hash": "d2aa2deaa51b406eb8b72a94429f5e1a",
        "starts_on": 3271,
        "ends_on": 3402,
        "selection_class": "ThirdParty",
        "selection_content": "данные, которые автоматически собираются внешними аналитическими системами, счетчиками, рекламными, поисковыми системами и т. п.,"
    },
    {
        "policy_hash": "d2aa2deaa51b406eb8b72a94429f5e1a",
        "starts_on": 5916,
        "ends_on": 5943,
        "selection_class": "ThirdParty",
        "selection_content": "неограниченному кругу лиц"
    },
    {
        "policy_hash": "d2aa2deaa51b406eb8b72a94429f5e1a",
        "starts_on": 6028,
        "ends_on": 6043,
        "selection_class": "ThirdParty",
        "selection_content": "третьим лицам"
    },
    {
        "policy_hash": "d2aa2deaa51b406eb8b72a94429f5e1a",
        "starts_on": 6259,
        "ends_on": 6274,
        "selection_class": "ThirdParty",
        "selection_content": "третьим лицам"
    },
    {
        "policy_hash": "d2aa2deaa51b406eb8b72a94429f5e1a",
        "starts_on": 6451,
        "ends_on": 6468,
        "selection_class": "ThirdParty",
        "selection_content": "третьей стороны"
    },
    {
        "policy_hash": "d2aa2deaa51b406eb8b72a94429f5e1a",
        "starts_on": 6486,
        "ends_on": 6539,
        "selection_class": "ThirdParty",
        "selection_content": "ным согласием на передачу персональной информации в"
    },
    {
        "policy_hash": "d2aa2deaa51b406eb8b72a94429f5e1a",
        "starts_on": 6544,
        "ends_on": 6562,
        "selection_class": "ThirdParty",
        "selection_content": "третьей стороны;"
    },
    {
        "policy_hash": "ea8a7f4e78516f6a6747447bfd24d4db",
        "starts_on": 2977,
        "ends_on": 3004,
        "selection_class": "ThirdParty",
        "selection_content": "неограниченного круга лиц"
    },
    {
        "policy_hash": "ea8a7f4e78516f6a6747447bfd24d4db",
        "starts_on": 3416,
        "ends_on": 3572,
        "selection_class": "ThirdParty",
        "selection_content": "направленные на раскрытие персональных данных определенному лицу или определенному кругу лиц.\n\n\n2. 12. распространение персональных данных любые действия,"
    },
    {
        "policy_hash": "ea8a7f4e78516f6a6747447bfd24d4db",
        "starts_on": 3617,
        "ends_on": 3644,
        "selection_class": "ThirdParty",
        "selection_content": "неопределенному кругу лиц"
    },
    {
        "policy_hash": "ea8a7f4e78516f6a6747447bfd24d4db",
        "starts_on": 3672,
        "ends_on": 3697,
        "selection_class": "ThirdParty",
        "selection_content": ") или на ознакомление с"
    },
    {
        "policy_hash": "ea8a7f4e78516f6a6747447bfd24d4db",
        "starts_on": 3718,
        "ends_on": 3824,
        "selection_class": "ThirdParty",
        "selection_content": "неограниченного круга лиц, в том числе обнародование персональных данных в средствах массовой информации"
    },
    {
        "policy_hash": "ea8a7f4e78516f6a6747447bfd24d4db",
        "starts_on": 4015,
        "ends_on": 4185,
        "selection_class": "ThirdParty",
        "selection_content": "персональных данных на территорию иностранного государства органу власти иностранного государства, иностранному физическому или иностранному юридическому лицу.\n\n\n2. 14."
    },
    {
        "policy_hash": "ea8a7f4e78516f6a6747447bfd24d4db",
        "starts_on": 8654,
        "ends_on": 8670,
        "selection_class": "ThirdParty",
        "selection_content": "гугл аналитика"
    },
    {
        "policy_hash": "ea8a7f4e78516f6a6747447bfd24d4db",
        "starts_on": 8671,
        "ends_on": 8679,
        "selection_class": "ThirdParty",
        "selection_content": "других"
    },
    {
        "policy_hash": "ea8a7f4e78516f6a6747447bfd24d4db",
        "starts_on": 10030,
        "ends_on": 10057,
        "selection_class": "ThirdParty",
        "selection_content": "неограниченным кругом лиц"
    },
    {
        "policy_hash": "ea8a7f4e78516f6a6747447bfd24d4db",
        "starts_on": 16081,
        "ends_on": 16108,
        "selection_class": "ThirdParty",
        "selection_content": "неограниченного круга лиц"
    },
    {
        "policy_hash": "ea8a7f4e78516f6a6747447bfd24d4db",
        "starts_on": 16973,
        "ends_on": 16988,
        "selection_class": "ThirdParty",
        "selection_content": "третьим лицам"
    },
    {
        "policy_hash": "ea8a7f4e78516f6a6747447bfd24d4db",
        "starts_on": 17159,
        "ends_on": 17174,
        "selection_class": "ThirdParty",
        "selection_content": "третьему лицу"
    },
    {
        "policy_hash": "ea8a7f4e78516f6a6747447bfd24d4db",
        "starts_on": 20352,
        "ends_on": 20379,
        "selection_class": "ThirdParty",
        "selection_content": "иностранным государством,"
    },
    {
        "policy_hash": "ea8a7f4e78516f6a6747447bfd24d4db",
        "starts_on": 20593,
        "ends_on": 20618,
        "selection_class": "ThirdParty",
        "selection_content": "иностранных государств,"
    },
    {
        "policy_hash": "ea8a7f4e78516f6a6747447bfd24d4db",
        "starts_on": 21027,
        "ends_on": 21042,
        "selection_class": "ThirdParty",
        "selection_content": "третьим лицам"
    },
    {
        "policy_hash": "f5c6b85960132390408dc801f230dc05",
        "starts_on": 4648,
        "ends_on": 4667,
        "selection_class": "ThirdParty",
        "selection_content": "с третьими лицами"
    },
    {
        "policy_hash": "f5c6b85960132390408dc801f230dc05",
        "starts_on": 6362,
        "ends_on": 6377,
        "selection_class": "ThirdParty",
        "selection_content": "третьим лицам"
    },
    {
        "policy_hash": "f5c6b85960132390408dc801f230dc05",
        "starts_on": 8882,
        "ends_on": 8899,
        "selection_class": "ThirdParty",
        "selection_content": "третьими лицами"
    }
]